khinsider.py
khinsider-1.0.0.dist-info/entry_points.txt
khinsider-1.0.0.dist-info/WHEEL
khinsider-1.0.0.dist-info/METADATA
khinsider-1.0.0.dist-info/RECORD
