Metadata-Version: 2.1
Name: khinsider
Version: 1.0.0
Summary: A script for khinsider mass downloads. Get video game soundtracks quickly and easily! Also a Python interface.
Home-page: https://github.com/SuperSonicHub1/khinsider
Author: Kyle Williams
Author-email: kyle.anthony.williams2@gmail.com
Requires-Python: >=3.8,<4.0
Classifier: Programming Language :: Python :: 3
Classifier: Programming Language :: Python :: 3.10
Classifier: Programming Language :: Python :: 3.8
Classifier: Programming Language :: Python :: 3.9
Requires-Dist: beautifulsoup4 (>=4.10.0,<5.0.0)
Requires-Dist: requests (>=2.26.0,<3.0.0)
Project-URL: Repository, https://github.com/SuperSonicHub1/khinsider.git
